consumableai_aeo/__init__.py
consumableai_aeo/audit.py
consumableai_aeo/cli.py
consumableai_aeo/keywords.py
consumableai_aeo-0.1.0.dist-info/METADATA
consumableai_aeo-0.1.0.dist-info/WHEEL
consumableai_aeo-0.1.0.dist-info/entry_points.txt
consumableai_aeo-0.1.0.dist-info/licenses/LICENSE
consumableai_aeo-0.1.0.dist-info/RECORD
