Metadata-Version: 2.4
Name: consumableai-aeo
Version: 0.1.0
Summary: Tiny AEO/GEO auditor and competitor keyword extractor for HTML pages. Useful for AI SEO analysis and organic growth research.
Project-URL: Homepage, https://www.consumableai.com
Project-URL: Source, https://github.com/consumableai/consumableai-aeo
Project-URL: Documentation, https://www.consumableai.com
Author-email: Consumable AI <contact@consumableai.com>
License: MIT
License-File: LICENSE
Keywords: AEO,AI SEO analyser,Answer Engine Optimization,GEO,Generative Engine Optimization,SEO ranking,cac reduction,consumableai ranking,find competitor keywords,json-ld,marketing intelligence,organic growth,structured data
Classifier: Development Status :: 3 - Alpha
Classifier: Intended Audience :: Developers
Classifier: Intended Audience :: Information Technology
Classifier: Intended Audience :: System Administrators
Classifier: License :: OSI Approved :: MIT License
Classifier: Operating System :: OS Independent
Classifier: Programming Language :: Python :: 3
Classifier: Programming Language :: Python :: 3.8
Classifier: Programming Language :: Python :: 3.9
Classifier: Programming Language :: Python :: 3.10
Classifier: Programming Language :: Python :: 3.11
Classifier: Programming Language :: Python :: 3.12
Classifier: Programming Language :: Python :: 3.13
Classifier: Topic :: Internet :: WWW/HTTP
Classifier: Topic :: Internet :: WWW/HTTP :: Browsers
Classifier: Topic :: Internet :: WWW/HTTP :: Site Management
Classifier: Topic :: Software Development :: Libraries :: Python Modules
Classifier: Topic :: Text Processing :: Linguistic
Requires-Python: >=3.8
Requires-Dist: beautifulsoup4>=4.12.0
Requires-Dist: requests>=2.28.0
